{
  "name": "Elaine Matos",
  "photo": "https://avatars.githubusercontent.com/u/69444237?v=4",
  "job": "Desenvolvedora Front End Jr",
  "location": "São Paulo - SP",
  "phone": "(11) 99770-1889",
  "email": "ejfmatos@outlook.com",
  "linkedin": "linkedin.com/in/elainejfmatos/",
  "skills": {
    "hardSkills": [
      {
        "name": "HTML",
        "logo": "https://raw.githubusercontent.com/enimatos/js-developer-portfolio/refs/heads/main/data/imgs/html.png"
      },
      {
        "name": "CSS",
        "logo": "https://raw.githubusercontent.com/enimatos/js-developer-portfolio/refs/heads/main/data/imgs/css.png"
      },
      {
        "name": "JavaScript",
        "logo": "https://raw.githubusercontent.com/enimatos/js-developer-portfolio/refs/heads/main/data/imgs/js.png"
      },
      {
        "name": "NodeJs",
        "logo": "https://raw.githubusercontent.com/enimatos/js-developer-portfolio/refs/heads/main/data/imgs/nodejs.png"
      },
      {
        "name": "VSCode",
        "logo": "https://raw.githubusercontent.com/enimatos/js-developer-portfolio/refs/heads/main/data/imgs/vscode.png"
      },
      {
        "name": "GitHub",
        "logo": "https://raw.githubusercontent.com/enimatos/js-developer-portfolio/refs/heads/main/data/imgs/github.png"
      }
    ],
    "softSkills": [
      "Empatia",
      "Trabalho em equipe",
      "Flexibilidade",
      "Facilidade de aprender",
      "Foco em resultado"
    ]
  },
  "languages": [
    "Português BR",
    "Inglês (intermediário em curso)",
    "Espanhol (básico)"
  ],
  "portfolio": [
    {
      "name": "Publicando Seu Portfólio Profissional no GitHub Pages",
      "url": "https://github.com/enimatos/js-developer-portfolio",
      "github": true
    },
    {
      "name": "Criando um Jogo do Detona Ralph com JavaScript",
      "url": "https://enimatos.github.io/dio-detona-ralph-js/",
      "github": true
    },
    {
      "name": "Criação de um jogo da memória",
      "url": "https://github.com/enimatos/jogo-da-memoria/tree/nova-entrega",
      "github": true
    },
    {
      "name": "Construindo uma Pokédex com JavaScript",
      "url": "https://github.com/enimatos/js-developer-pokedex",
      "github": true
    },
    {
      "name": "Primeiro Portfólio - Oracle-One",
      "url": "https://portfolio-nine-bay-27.vercel.app/",
      "github": false
    },
    {
      "name": "D3c0dif!q - Oracle-One",
      "url": "https://decodificador-oracle-one-bay.vercel.app/",
      "github": false
    },
    {
      "name": "Jogo do Número Secreto",
      "url": "https://jogo-do-numero-secreto-weld-mu.vercel.app/",
      "github": false
    },
    {
      "name": "Yu-Gi-Oh | Jo-ken-po Edition",
      "url": "https://github.com/enimatos/js-yugioh-assets/tree/versao-desafio",
      "github": true
    }
  ],
  "certifications": [
    {
      "name": "AWS Cloud Practitioner",
      "period": "2023"
    },
    {
      "name": "Azure - SC-900: Microsoft Security, Compliance, and Identity Fundamentals",
      "period": "2023"
    },
    {
      "name": "AWS Solutions Architect - Associate (SAA-C03)",
      "period": "2024"
    }    
  ],
  "professionalExperience": [
    {
      "name": "Asssitente de monitoramento / O2B",
      "period": "Set 2024 - Mar 2025",
      "description": "Monitoramento de eventos no Datadog, encaminhamento de erros sistêmicos para equipes internas e acompanhamento de melhoria e identificação de erro em sala de crise."
    },
    {
      "name": "Analista de Suporte TI I / Cleartech",
      "period": "Set 2021 - Jun 2023",
      "description": "Monitoramento de alarmes via Zabbix  para identificação de erros sistêmicos, encaminhamento de demandas do Jira Service Desk para equipes responsáveis, manutenção de usuários em sistemas de comunicações e execução de demandas internas (checklists e passagem de turno), assegurando a continuidade e a eficiência das operações."
    },
    {
      "name": "Analista de Monitoramento e Produção / Connectcom",
      "period": "Jan 2021 - Set 2021",
      "description": "Montagem e liberação de processos com o Unisys 2200,  monitoramento de links,  programação de backups, restauração de dados com o Commvault, e controle de acesso físico ao DataCenter."
    }
  ],
  "formacaoAcademica": [
    {
      "name": "MBA Executivo em Auditoria, Gerenciamento de Riscos e Compliance",
      "period": "Nov 2017 - Dez 2018",
      "institution": " Universidade de Santo Amaro (Unisa)."
    },
    {
      "name": "Tecnologia em Processamento de Dados",
      "period": "Fev 2006 - Dez 2008",
      "institution": "Universidade Bandeirante de São Paulo (Uniban)"
    }
  ]
}
